pfdr/__init__.py
pfdr/cli.py
pfdr/config.py
pfdr/dblp.py
pfdr/deepseek.py
pfdr/llm.py
pfdr/models.py
pfdr/openai_client.py
pfdr/state.py
pfdr/storage.py
pfdr/tasks.py
pfdr/webui.py
pfdr/services/__init__.py
pfdr/services/configuration.py
pfdr/services/enrichment.py
pfdr/services/ingestion.py
pfdr/services/search.py
pfdr/services/tasks.py
pfdr/webui/static/app.js
pfdr/webui/static/styles.css
pfdr/webui/templates/index.html
pfdr-0.1.3.dist-info/METADATA
pfdr-0.1.3.dist-info/WHEEL
pfdr-0.1.3.dist-info/entry_points.txt
pfdr-0.1.3.dist-info/licenses/LICENSE
pfdr-0.1.3.dist-info/RECORD
