Metadata-Version: 2.4
Name: pfdr
Version: 0.1.3
Summary: DBLP ingestion and AI-powered querying for academic papers
Project-URL: Homepage, https://github.com/enkerewpo/pfdr
Project-URL: Repository, https://github.com/enkerewpo/pfdr
Project-URL: Issues, https://github.com/enkerewpo/pfdr/issues
Project-URL: Documentation, https://github.com/enkerewpo/pfdr#readme
Author-email: wheatfox <wheatfox17@icloud.com>
Maintainer-email: wheatfox <wheatfox17@icloud.com>
License: MIT License
License-File: LICENSE
Keywords: AI,LLM,academic,dblp,papers,research
Classifier: Development Status :: 3 - Alpha
Classifier: Intended Audience :: Developers
Classifier: License :: OSI Approved :: MIT License
Classifier: Operating System :: OS Independent
Classifier: Programming Language :: Python :: 3
Classifier: Programming Language :: Python :: 3.8
Classifier: Programming Language :: Python :: 3.9
Classifier: Programming Language :: Python :: 3.10
Classifier: Programming Language :: Python :: 3.11
Classifier: Programming Language :: Python :: 3.12
Requires-Python: >=3.8
Requires-Dist: aiohttp>=3.8.0
Requires-Dist: fastapi>=0.104.0
Requires-Dist: jinja2>=3.1.0
Requires-Dist: python-multipart>=0.0.6
Requires-Dist: pyyaml>=6.0
Requires-Dist: requests
Requires-Dist: typer[all]>=0.9.0
Requires-Dist: uvicorn[standard]>=0.24.0
Provides-Extra: dev
Requires-Dist: flake8; extra == 'dev'
Requires-Dist: pytest; extra == 'dev'
Requires-Dist: ruff; extra == 'dev'
